cid/__init__.py
cid/cid.py
py_cid-0.2.1.dist-info/DESCRIPTION.rst
py_cid-0.2.1.dist-info/METADATA
py_cid-0.2.1.dist-info/RECORD
py_cid-0.2.1.dist-info/WHEEL
py_cid-0.2.1.dist-info/metadata.json
py_cid-0.2.1.dist-info/top_level.txt
