Metadata-Version: 2.0
Name: py-cid
Version: 0.2.1
Summary: Self-describing content-addressed identifiers for distributed systems
Home-page: https://github.com/ipld/py-cid
Author: Dhruv Baldawa
Author-email: dhruv@dhruvb.com
License: MIT license
Keywords: cid
Platform: UNKNOWN
Classifier: Development Status :: 2 - Pre-Alpha
Classifier: Intended Audience :: Developers
Classifier: License :: OSI Approved :: MIT License
Classifier: Natural Language :: English
Classifier: Programming Language :: Python :: 3
Classifier: Programming Language :: Python :: 3.3
Classifier: Programming Language :: Python :: 3.4
Classifier: Programming Language :: Python :: 3.5
Classifier: Programming Language :: Python :: 3.6
Requires-Dist: base58 (>=1.0.2,<2.0)
Requires-Dist: morphys (<2.0,>=1.0)
Requires-Dist: py-multibase (>=1.0.0,<2.0.0)
Requires-Dist: py-multicodec (<0.2.0)
Requires-Dist: py-multihash (>=0.2.0,<1.0.0)
